quick_sentiments/__init__.py
quick_sentiments/pipeline.py
quick_sentiments/predict.py
quick_sentiments/preprocess.py
quick_sentiments/spacy_preprocess.py
quick_sentiments/virtual_environment_setup.py
quick_sentiments/ml_algo/XGB.py
quick_sentiments/ml_algo/__init__.py
quick_sentiments/ml_algo/logit.py
quick_sentiments/ml_algo/nb.py
quick_sentiments/ml_algo/nn.py
quick_sentiments/ml_algo/rf.py
quick_sentiments/vect/BOW.py
quick_sentiments/vect/__init__.py
quick_sentiments/vect/glove_100.py
quick_sentiments/vect/glove_200.py
quick_sentiments/vect/glove_25.py
quick_sentiments/vect/glove_50.py
quick_sentiments/vect/tf.py
quick_sentiments/vect/tfidf.py
quick_sentiments/vect/wv.py
quicktest/Lib/site-packages/_distutils_hack/__init__.py
quicktest/Lib/site-packages/_distutils_hack/override.py
quicktest/Lib/site-packages/build/__init__.py
quicktest/Lib/site-packages/build/__main__.py
quicktest/Lib/site-packages/build/_builder.py
quicktest/Lib/site-packages/build/_ctx.py
quicktest/Lib/site-packages/build/_exceptions.py
quicktest/Lib/site-packages/build/_types.py
quicktest/Lib/site-packages/build/_util.py
quicktest/Lib/site-packages/build/env.py
quicktest/Lib/site-packages/build/py.typed
quicktest/Lib/site-packages/build/util.py
quicktest/Lib/site-packages/build/_compat/__init__.py
quicktest/Lib/site-packages/build/_compat/importlib.py
quicktest/Lib/site-packages/build/_compat/tarfile.py
quicktest/Lib/site-packages/build/_compat/tomllib.py
quicktest/Lib/site-packages/colorama/__init__.py
quicktest/Lib/site-packages/colorama/ansi.py
quicktest/Lib/site-packages/colorama/ansitowin32.py
quicktest/Lib/site-packages/colorama/initialise.py
quicktest/Lib/site-packages/colorama/win32.py
quicktest/Lib/site-packages/colorama/winterm.py
quicktest/Lib/site-packages/colorama/tests/__init__.py
quicktest/Lib/site-packages/colorama/tests/ansi_test.py
quicktest/Lib/site-packages/colorama/tests/ansitowin32_test.py
quicktest/Lib/site-packages/colorama/tests/initialise_test.py
quick_sentiments-0.2.9.dist-info/METADATA
quick_sentiments-0.2.9.dist-info/WHEEL
quick_sentiments-0.2.9.dist-info/top_level.txt
quick_sentiments-0.2.9.dist-info/RECORD
