Metadata-Version: 2.4
Name: quick-sentiments
Version: 0.2.9
Summary: Sentiment Analysis pipeline
Author: Alabhya Dahal
Author-email: Alabhya Dahal <alabhya.dahal@gmail.com>
License: MIT License
Project-URL: Homepage, https://github.com/AlabhyaMe/Sentiments-Analysis
Classifier: Development Status :: 4 - Beta
Classifier: Intended Audience :: Developers
Classifier: Intended Audience :: Science/Research
Classifier: License :: OSI Approved :: MIT License
Classifier: Operating System :: OS Independent
Classifier: Programming Language :: Python :: 3
Classifier: Programming Language :: Python :: 3.8
Classifier: Programming Language :: Python :: 3.9
Classifier: Programming Language :: Python :: 3.10
Classifier: Topic :: Scientific/Engineering
Classifier: Topic :: Software Development :: Libraries :: Python Modules
Classifier: Topic :: Text Processing :: Linguistic
Requires-Python: >=3.8
Requires-Dist: numpy<2.0.0,>=1.23.0
Requires-Dist: pandas>=1.3.0
Requires-Dist: scikit-learn>=1.0.0
Requires-Dist: polars<0.20.0,>=0.19.5
Requires-Dist: gensim>4.0.0
Requires-Dist: nltk==3.8.1
Requires-Dist: xgboost==3.0.2
Requires-Dist: scipy<2.0.0,>=1.9.0
Provides-Extra: dev
Requires-Dist: pytest>=6.0; extra == "dev"
Requires-Dist: black>=22.0; extra == "dev"
Requires-Dist: twine; extra == "dev"
Requires-Dist: build; extra == "dev"
Dynamic: author
